oa_water_jug.py
oa_water_jug-0.0.3.dist-info/LICENSE
oa_water_jug-0.0.3.dist-info/METADATA
oa_water_jug-0.0.3.dist-info/WHEEL
oa_water_jug-0.0.3.dist-info/top_level.txt
oa_water_jug-0.0.3.dist-info/RECORD
