Metadata-Version: 2.1
Name: oa-water-jug
Version: 0.0.3
Summary: Water Jug Problem
Author: The OA
Classifier: Programming Language :: Python :: 3
Classifier: License :: OSI Approved :: MIT License
Classifier: Operating System :: OS Independent
Requires-Python: >=3.6
License-File: LICENSE
